CHANGELOG.txt
LICENSE.txt
MANIFEST.in
README.md
setup.py
cust/__init__.py
cust.egg-info/PKG-INFO
cust.egg-info/SOURCES.txt
cust.egg-info/dependency_links.txt
cust.egg-info/top_level.txt