Metadata-Version: 2.1
Name: cust
Version: 0.0.3
Summary: Utils
Home-page: UNKNOWN
Author: Miguel Malgarezi
Author-email: miguelmalgarezi@gmail.com
License: MIT
Keywords: utils
Platform: UNKNOWN
Classifier: Development Status :: 5 - Production/Stable
Classifier: Intended Audience :: Education
Classifier: Operating System :: Microsoft :: Windows :: Windows 10
Classifier: License :: OSI Approved :: MIT License
Classifier: Programming Language :: Python :: 3
